Atividades/Revisão Prova 1/exercicio_02.v
module f(output s, input a, input b, input c);
  wire w1, w2, w3, w4;
  not NOT_1 (w1, b);
  not NOT_2 (w2, c);
  and AND_1 (w3, a, w2);
  and AND_2 (w4, a, w1, c);
  or OR_1 (s, w3, w4);
endmodule

Atividades/Revisão Prova 1/testbench.v
module testbench;
  reg a, b, c;
  wire s;
  
  // Instanciando o módulo f
  f uut (s, a, b, c);
  
  // Testando todas as combinações de entrada
  initial begin
    $dumpfile("tabela_verdade.vcd");
    $dumpvars(0, testbench);
    
    // Gerando tabela-verdade
    for (a = 0; a <= 1; a = a + 1) begin
      for (b = 0; b <= 1; b = b + 1) begin
        for (c = 0; c <= 1; c = c + 1) begin
          #1;
          $display("%b %b %b | %b", a, b, c, s);
        end
      end
    end
    
    $finish;
  end
endmodule

Atividades/Revisão Prova 1/tabela_verdade.vcd
$date
	Sun Oct 08 20:32:39 2023
$end
$version
	Icarus Verilog
$end
$timescale
	1s
$end
$scope module testbench $end
$var wire 1 ! s $end
$var reg 1 " a $end
$var reg 1 # b $end
$var reg 1 $ c $end
$scope module uut $end
$var wire 1 " a $end
$var wire 1 # b $end
$var wire 1 $ c $end
$var wire 1 ! s $end
$var wire 1 % w1 $end
$var wire 1 & w2 $end
$var wire 1 ' w3 $end
$var wire 1 ( w4 $end
$upscope $end
$upscope $end
$enddefinitions $end
$comment Show the parameter values. $end
$dumpall
$end
#0
$dumpvars
0(
0'
1&
1%
0$
0#
0"
0!
$end
#1
0&
1$
#2
1&
0$
#3
0&
1$
#4
1&
0$
#5
0&
1$
#6
1&
0$
#7
0&
1$
#8
1&
0$
#9
0&
1$
#10
1&
0$
#11
0&
1$
#12
1&
0$
#13
0&
1$
#14
1&
0$
#15
0&
1$
#16
1&
0$
#17
0&
1$
#18
1&
0$
#19
0&
1$
#20
1&
0$
#21
0&
1$
#22
1&
0$
#23
0&
1$
#24
1&
0$
#25
0&
1$
#26
1&
0$
#27
0&
1$
#28
1&
0$
#29
0&
1$
#30
1&
0$
#31
0&
1$
#32
1&
0$
#33
0&
1$
#34
1&
0$
#35
0&
1$
#36
1&
0$
#37
0&
1$
#38
1&
0$
#39
0&
1$
#40
1&
0$
#41
0&
1$
#42
1&
0$
#43
0&
1$
#44
1&
0$
#45
0&
1$
#46
1&
0$
#47
0&
1$
#48
1&
0$
#49
0&
1$
#50
1&
0$
#51
0&
1$
#52
1&
0$
#53
0&
1$
#54
1&
0$
#55
0&
1$
#56
1&
0$
#57
0&
1$
#58
1&
0$
#59
0&
1$
#60
1&
0$
#61
0&
1$
#62
1&
0$
#63
0&
1$
#64
1&
0$
#65
0&
1$
#66
1&
0$
#67
0&
1$
#68
1&
0$
#69
0&
1$
#70
1&
0$
#71
0&
1$
#72
1&
0$
#73
0&
1$
#74
1&
0$
#75
0&
1$
#76
1&
0$
#77
0&
1$
#78
1&
0$
#79
0&
1$
#80
1&
0$
#81
0&
1$
#82
1&
0$
#83
0&
1$
#84
1&
0$
#85
0&
1$
#86
1&
0$
#87
0&
1$
#88
1&
0$
#89
0&
1$
#90
1&
0$
#91
0&
1$
#92
1&
0$
#93
0&
1$
#94
1&
0$
#95
0&
1$
#96
1&
0$
#97
0&
1$
#98
1&
0$
#99
0&
1$
#100
1&
0$
#101
0&
1$
#102
1&
0$
#103
0&
1$
#104
1&
0$
#105
0&
1$
#106
1&
0$
#107
0&
1$
#108
1&
0$
#109
0&
1$
#110
1&
0$
#111
0&
1$
#112
1&
0$
#113
0&
1$
#114
1&
0$
#115
0&
1$
#116
1&
0$
#117
0&
1$
#118
1&
0$
#119
0&
1$
#120
1&
0$
#121
0&
1$
#122
1&
0$
#123
0&
1$
#124
1&
0$
#125
0&
1$
#126
1&
0$
#127
0&
1$
#128
1&
0$
#129
0&
1$
#130
1&
0$
#131
0&
1$
#132
1&
0$
#133
0&
1$
#134
1&
0$
#135
0&
1$
#136
1&
0$
#137
0&
1$
#138
1&
0$
#139
0&
1$
#140
1&
0$
#141
0&
1$
#142
1&
0$
#143
0&
1$
#144
1&
0$
#145
0&
1$
#146
1&
0$
#147
0&
1$
#148
1&
0$
#149
0&
1$
#150
1&
0$
#151
0&
1$
#152
1&
0$
#153
0&
1$
#154
1&
0$
#155
0&
1$
#156
1&
0$
#157
0&
1$
#158
1&
0$
#159
0&
1$
#160
1&
0$
#161
0&
1$
#162
1&
0$
#163
0&
1$
#164
1&
0$
#165
0&
1$
#166
1&
0$
#167
0&
1$
#168
1&
0$
#169
0&
1$
#170
1&
0$
#171
0&
1$
#172
1&
0$
#173
0&
1$
#174
1&
0$
#175
0&
1$
#176
1&
0$
#177
0&
1$
#178
1&
0$
#179
0&
1$
#180
1&
0$
#181
0&
1$
#182
1&
0$
#183
0&
1$
#184
1&
0$
#185
0&
1$
#186
1&
0$
#187
0&
1$
#188
1&
0$
#189
0&
1$
#190
1&
0$
#191
0&
1$
#192
1&
0$
#193
0&
1$
#194
1&
0$
#195
0&
1$
#196
1&
0$
#197
0&
1$
#198
1&
0$
#199
0&
1$
#200
1&
0$
#201
0&
1$
#202
1&
0$
#203
0&
1$
#204
1&
0$
#205
0&
1$
#206
1&
0$
#207
0&
1$
#208
1&
0$
#209
0&
1$
#210
1&
0$
#211
0&
1$
#212
1&
0$
#213
0&
1$
#214
1&
0$
#215
0&
1$
#216
1&
0$
#217
0&
1$
#218
1&
0$
#219
0&
1$
#220
1&
0$
#221
0&
1$
#222
1&
0$
#223
0&
1$
#224
1&
0$
#225
0&
1$
#226
1&
0$
#227
0&
1$
#228
1&
0$
#229
0&
1$
#230
1&
0$
#231
0&
1$
#232
1&
0$
#233
0&
1$
#234
1&
0$
#235
0&
1$
#236
1&
0$
#237
0&
1$
#238
1&
0$
#239
0&
1$
#240
1&
0$
#241
0&
1$
#242
1&
0$
#243
0&
1$
#244
1&
0$
#245
0&
1$
#246
1&
0$
#247
0&
1$
#248
1&
0$
#249
0&
1$
#250
1&
0$
#251
0&
1$
#252
1&
0$
#253
0&
1$
#254
1&
0$
#255
0&
1$
#256
1&
0$
#257
0&
1$
#258
1&
0$
#259
0&
1$
#260
1&
0$
#261
0&
1$
#262
1&
0$
#263
0&
1$
#264
1&
0$
#265
0&
1$
#266
1&
0$
#267
0&
1$
#268
1&
0$
#269
0&
1$
#270
1&
0$
#271
0&
1$
#272
1&
0$
#273
0&
1$
#274
1&
0$
#275
0&
1$
#276
1&
0$
#277
0&
1$
#278
1&
0$
#279
0&
1$
#280
1&
0$
#281
0&
1$
#282
1&
0$
#283
0&
1$
#284
1&
0$
#285
0&
1$
#286
1&
0$
#287
0&
1$
#288
1&
0$
#289
0&
1$
#290
1&
0$
#291
0&
1$
#292
1&
0$
#293
0&
1$
#294
1&
0$
#295
0&
1$
#296
1&
0$
#297
0&
1$
#298
1&
0$
#299
0&
1$
#300
1&
0$
#301
0&
1$
#302
1&
0$
#303
0&
1$
#304
1&
0$
#305
0&
1$
#306
1&
0$
#307
0&
1$
#308
1&
0$
#309
0&
1$
#310
1&
0$
#311
0&
1$
#312
1&
0$
#313
0&
1$
#314
1&
0$
#315
0&
1$
#316
1&
0$
#317
0&
1$
#318
1&
0$
#319
0&
1$
#320
1&
0$
#321
0&
1$
#322
1&
0$
#323
0&
1$
#324
1&
0$
#325
0&
1$
#326
1&
0$
#327
0&
1$
#328
1&
0$
#329
0&
1$
#330
1&
0$
#331
0&
1$
#332
1&
0$
#333
0&
1$
#334
1&
0$
#335
0&
1$
#336
1&
0$
#337
0&
1$
#338
1&
0$
#339
0&
1$
#340
1&
0$
#341
0&
1$
#342
1&
0$
#343
0&
1$
#344
1&
0$
#345
0&
1$
#346
1&
0$
#347
0&
1$
#348
1&
0$
#349
0&
1$
#350
1&
0$
#351
0&
1$
#352
1&
0$
#353
0&
1$
#354
1&
0$
#355
0&
1$
#356
1&
0$
#357
0&
1$
#358
1&
0$
#359
0&
1$
#360
1&
0$
#361
0&
1$
#362
1&
0$
#363
0&
1$
#364
1&
0$
#365
0&
1$
#366
1&
0$
#367
0&
1$
#368
1&
0$
#369
0&
1$
#370
1&
0$
#371
0&
1$
#372
1&
0$
#373
0&
1$
#374
1&
0$
#375
0&
1$
#376
1&
0$
#377
0&
1$
#378
1&
0$
#379
0&
1$
#380
1&
0$
#381
0&
1$
#382
1&
0$
#383
0&
1$
#384
1&
0$
#385
0&
1$
#386
1&
0$
#387
0&
1$
#388
1&
0$
#389
0&
1$
#390
1&
0$
#391
0&
1$
#392
1&
0$
#393
0&
1$
#394
1&
0$
#395
0&
1$
#396
1&
0$
#397
0&
1$
#398
1&
0$
#399
0&
1$
#400
1&
0$
#401
0&
1$
#402
1&
0$
#403
0&
1$
#404
1&
0$
#405
0&
1$
#406
1&
0$
#407
0&
1$
#408
1&
0$
#409
0&
1$
#410
1&
0$
#411
0&
1$
#412
1&
0$
#413
0&
1$
#414
1&
0$
#415
0&
1$
#416
1&
0$
#417
0&
1$
#418
1&
0$
#419
0&
1$
#420
1&
0$
#421
0&
1$
#422
1&
0$
#423
0&
1$
#424
1&
0$
#425
0&
1$
#426
1&
0$
#427
0&
1$
#428
1&
0$
#429
0&
1$
#430
1&
0$
#431
0&
1$
#432
1&
0$
#433
0&
1$
#434
1&
0$
#435
0&
1$
#436
1&
0$
#437
0&
1$
#438
1&
0$
#439
0&
1$
#440
1&
0$
#441
0&
1$
#442
1&
0$
#443
0&
1$
#444
1&
0$
#445
0&
1$
#446
1&
0$
#447
0&
1$
#448
1&
0$
#449
0&
1$
#450
1&
0$
#451
0&
1$
#452
1&
0$
#453
0&
1$
#454
1&
0$
#455
0&
1$
#456
1&
0$
#457
0&
1$
#458
1&
0$
#459
0&
1$
#460
1&
0$
#461
0&
1$
#462
1&
0$
#463
0&
1$
#464
1&
0$
#465
0&
1$
#466
1&
0$
#467
0&
1$
#468
1&
0$
#469
0&
1$
#470
1&
0$
#471
0&
1$
#472
1&
0$
#473
0&
1$
#474
1&
0$
#475
0&
1$
#476
1&
0$
#477
0&
1$
#478
1&
0$
#479
0&
1$
#480
1&
0$
#481
0&
1$
#482
1&
0$
#483
0&
1$
#484
1&
0$
#485
0&
1$
#486
1&
0$
#487
0&
1$
#488
1&
0$
#489
0&
1$
#490
1&
0$
#491
0&
1$
#492
1&
0$
#493
0&
1$
#494
1&
0$
#495
0&
1$
#496
1&
0$
#497
0&
1$
#498
1&
0$
#499
0&
1$
#500
1&
0$
#501
0&
1$
#502
1&
0$
#503
0&
1$
#504
1&
0$
#505
0&
1$
#506
1&
0$
#507
0&
1$
#508
1&
0$
#509
0&
1$
#510
1&
0$
#511
0&
1$
#512
1&
0$
#513
0&
1$
#514
1&
0$
#515
0&
1$
#516
1&
0$
#517
0&
1$
#518
1&
0$
#519
0&
1$
#520
1&
0$
#521
0&
1$
#522
1&
0$
#523
0&
1$
#524
1&
0$
#525
0&
1$
#526
1&
0$
#527
0&
1$
#528
1&
0$
#529
0&
1$
#530
1&
0$
#531
0&
1$
#532
1&
0$
#533
0&
1$
#534
1&
0$
#535
0&
1$
#536
1&
0$
#537
0&
1$
#538
1&
0$
#539
0&
1$
#540
1&
0$
#541
0&
1$
#542
1&
0$
#543
0&
1$
#544
1&
0$
#545
0&
1$
#546
1&
0$
#547
0&
1$
#548
1&
0$
#549
0&
1$
#550
1&
0$
#551
0&
1$
#552
1&
0$
#553
0&
1$
#554
1&
0$
#555
0&
1$
#556
1&
0$
#557
0&
1$
#558
1&
0$
#559
0&
1$
#560
1&
0$
#561
0&
1$
#562
1&
0$
#563
0&
1$
#564
1&
0$
#565
0&
1$
#566
1&
0$
#567
0&
1$
#568
1&
0$
#569
0&
1$
#570
1&
0$
#571
0&
1$
#572
1&
0$
#573
0&
1$
#574
1&
0$
#575
0&
1$
#576
1&
0$
#577
0&
1$
#578
1&
0$
#579
0&
1$
#580
1&
0$
#581
0&
1$
#582
1&
0$
#583
0&
1$
#584
1&
0$
#585
0&
1$
#586
1&
0$
#587
0&
1$
#588
1&
0$
#589
0&
1$
#590
1&
0$
#591
0&
1$
#592
1&
0$
#593
0&
1$
#594
1&
0$
#595
0&
1$
#596
1&
0$
#597
0&
1$
#598
1&
0$
#599
0&
1$
#600
1&
0$
#601
0&
1$
#602
1&
0$
#603
0&
1$
#604
1&
0$
#605
0&
1$
#606
1&
0$
#607
0&
1$
#608
1&
0$
#609
0&
1$
#610
1&
0$
#611
0&
1$
#612
1&
0$
#613
0&
1$
#614
1&
0$
#615
0&
1$
#616
1&
0$
#617
0&
1$
#618
1&
0$
#619
0&
1$
#620
1&
0$
#621
0&
1$
#622
1&
0$
#623
0&
1$
#624
1&
0$
#625
0&
1$
#626
1&
0$
#627
0&
1$
#628
1&
0$
#629
0&
1$
#630
1&
0$
#631
0&
1$
#632
1&
0$
#633
0&
1$
#634
1&
0$
#635
0&
1$
#636
1&
0$
#637
0&
1$
#638
1&
0$
#639
0&
1$
#640
1&
0$
#641
0&
1$
#642
1&
0$
#643
0&
1$
#644
1&
0$
#645
0&
1$
#646
1&
0$
#647
0&
1$
#648
1&
0$
#649
0&
1$
#650
1&
0$
#651
0&
1$
#652
1&
0$
#653
0&
1$
#654
1&
0$
#655
0&
1$
#656
1&
0$
#657
0&
1$
#658
1&
0$
#659
0&
1$
#660
1&
0$
#661
0&
1$
#662
1&
0$
#663
0&
1$
#664
1&
0$
#665
0&
1$
#666
1&
0$
#667
0&
1$
#668
1&
0$
#669
0&
1$
#670
1&
0$
#671
0&
1$
#672
1&
0$
#673
0&
1$
#674
1&
0$
#675
0&
1$
#676
1&
0$
#677
0&
1$
#678
1&
0$
#679
0&
1$
#680
1&
0$
#681
0&
1$
#682
1&
0$
#683
0&
1$
#684
1&
0$
#685
0&
1$
#686
1&
0$
#687
0&
1$
#688
1&
0$
#689
0&
1$
#690
1&
0$
#691
0&
1$
#692
1&
0$
#693
0&
1$
#694
1&
0$
#695
0&
1$
#696
1&
0$
#697
0&
1$
#698
1&
0$
#699
0&
1$
#700
1&
0$
#701
0&
1$
#702
1&
0$
#703
0&
1$
#704
1&
0$
#705
0&
1$
#706
1&
0$
#707
0&
1$
#708
1&
0$
#709
0&
1$
#710
1&
0$
#711
0&
1$
#712
1&
0$
#713
0&
1$
#714
1&
0$
#715
0&
1$
#716
1&
0$
#717
0&
1$
#718
1&
0$
#719
0&
1$
#720
1&
0$
#721
0&
1$
#722
1&
0$
#723
0&
1$
#724
1&
0$
#725
0&
1$
#726
1&
0$
#727
0&
1$
#728
1&
0$
#729
0&
1$
#730
1&
0$
#731
0&
1$
#732
1&
0$
#733
0&
1$
#734
1&
0$
#735
0&
1$
#736
1&
0$
#737
0&
1$
#738
1&
0$
#739
0&
1$
#740
1&
0$
#741
0&
1$
#742
1&
0$
#743
0&
1$
#744
1&
0$
#745
0&
1$
#746
1&
0$
#747
0&
1$
#748
1&
0$
#749
0&
1$
#750
1&
0$
#751
0&
1$
#752
1&
0$
#753
0&
1$
#754
1&
0$
#755
0&
1$
#756
1&
0$
#757
0&
1$
#758
1&
0$
#759
0&
1$
#760
1&
0$
#761
0&
1$
#762
1&
0$
#763
0&
1$
#764
1&
0$
#765
0&
1$
#766
1&
0$
#767
0&
1$
#768
1&
0$
#769
0&
1$
#770
1&
0$
#771
0&
1$
#772
1&
0$
#773
0&
1$
#774
1&
0$
#775
0&
1$
#776
1&
0$
#777
0&
1$
#778
1&
0$
#779
0&
1$
#780
1&
0$
#781
0&
1$
#782
1&
0$
#783
0&
1$
#784
1&
0$
#785
0&
1$
#786
1&
0$
#787
0&
1$
#788
1&
0$
#789
0&
1$
#790
1&
0$
#791
0&
1$
#792
1&
0$
#793
0&
1$
#794
1&
0$
#795
0&
1$
#796
1&
0$
#797
0&
1$
#798
1&
0$
#799
0&
1$
#800
1&
0$
#801
0&
1$
#802
1&
0$
#803
0&
1$
#804
1&
0$
#805
0&
1$
#806
1&
0$
#807
0&
1$
#808
1&
0$
#809
0&
1$
#810
1&
0$
#811
0&
1$
#812
1&
0$
#813
0&
1$
#814
1&
0$
#815
0&
1$
#816
1&
0$
#817
0&
1$
#818
1&
0$
#819
0&
1$
#820
1&
0$
#821
0&
1$
#822
1&
0$
#823
0&
1$
#824
1&
0$
#825
0&
1$
#826
1&
0$
#827
0&
1$
#828
1&
0$
#829
0&
1$
#830
1&
0$
#831
0&
1$
#832
1&
0$
#833
0&
1$
#834
1&
0$
#835
0&
1$
#836
1&
0$
#837
0&
1$
#838
1&
0$
#839
0&
1$
#840
1&
0$
#841
0&
1$
#842
1&
0$
#843
0&
1$
#844
1&
0$
#845
0&
1$
#846
1&
0$
#847
0&
1$
#848
1&
0$
#849
0&
1$
#850
1&
0$
#851
0&
1$
#852
1&
0$
#853
0&
1$
#854
1&
0$
#855
0&
1$
#856
1&
0$
#857
0&
1$
#858
1&
0$
#859
0&
1$
#860
1&
0$
#861
0&
1$
#862
1&
0$
#863
0&
1$
#864
1&
0$
#865
0&
1$
#866
1&
0$
#867
0&
1$
#868
1&
0$
#869
0&
1$
#870
1&
0$
#871
0&
1$
#872
1&
0$
#873
0&
1$
#874
1&
0$
#875
0&
1$
#876
1&
0$
#877
0&
1$
#878
1&
0$
#879
0&
1$
#880
1&
0$
#881
0&
1$
#882
1&
0$
#883
0&
1$
#884
1&
0$
#885
0&
1$
#886
1&
0$
#887
0&
1$
#888
1&
0$
#889
0&
1$
#890
1&
0$
#891
0&
1$
#892
1&
0$
#893
0&
1$
#894
1&
0$
#895
0&
1$
#896
1&
0$
#897
0&
1$
#898
1&
0$
#899
0&
1$
#900
1&
0$
#901
0&
1$
#902
1&
0$
#903
0&
1$
#904
1&
0$
#905
0&
1$
#906
1&
0$
#907
0&
1$
#908
1&
0$
#909
0&
1$
#910
1&
0$
#911
0&
1$
#912
1&
0$
#913
0&
1$
#914
1&
0$
#915
0&
1$
#916
1&
0$
#917
0&
1$
#918
1&
0$
#919
0&
1$
#920
1&
0$
#921
0&
1$
#922
1&
0$
#923
0&
1$
#924
1&
0$
#925
0&
1$
#926
1&
0$
#927
0&
1$
#928
1&
0$
#929
0&
1$
#930
1&
0$
#931
0&
1$
#932
1&
0$
#933
0&
1$
#934
1&
0$
#935
0&
1$
#936
1&
0$
#937
0&
1$
#938
1&
0$
#939
0&
1$
#940
1&
0$
#941
0&
1$
#942
1&
0$
#943
0&
1$
#944
1&
0$
#945
0&
1$
#946
1&
0$
#947
0&
1$
#948
1&
0$
#949
0&
1$
#950
1&
0$
#951
0&
1$
#952
1&
0$
#953
0&
1$
#954
1&
0$
#955
0&
1$
#956
1&
0$
#957
0&
1$
#958
1&
0$
#959
0&
1$
#960
1&
0$
#961
0&
1$
#962
1&
0$
#963
0&
1$
#964
1&
0$
#965
0&
1$
#966
1&
0$
#967
0&
1$
#968
1&
0$
#969
0&
1$
#970
1&
0$
#971
0&
1$
#972
1&
0$
#973
0&
1$
#974
1&
0$
#975
0&
1$
#976
1&
0$
#977
0&
1$
#978
1&
0$
#979
0&
1$
#980
1&
0$
#981
0&
1$
#982
1&
0$
#983
0&
1$
#984
1&
0$
#985
0&
1$
#986
1&
0$
#987
0&
1$
#988
1&
0$
#989
0&
1$
#990
1&
0$
#991
0&
1$
#992
1&
0$
#993
0&
1$
#994
1&
0$
#995
0&
1$
#996
1&
0$
#997
0&
1$
#998
1&
0$
#999
0&
1$
#1000
1&
0$
#1001
0&
1$
#1002
1&
0$
#1003
0&
1$
#1004
1&
0$
#1005
0&
1$
#1006
1&
0$
#1007
0&
1$
#1008
1&
0$
#1009
0&
1$
#1010
1&
0$
#1011
0&
1$
#1012
1&
0$
#1013
0&
1$
#1014
1&
0$
#1015
0&
1$
#1016
1&
0$
#1017
0&
1$
#1018
1&
0$
#1019
0&
1$
#1020
1&
0$
#1021
0&
1$
#1022
1&
0$
#1023
0&
1$
#1024
1&
0$
#1025
0&
1$
#1026
1&
0$
#1027
0&
1$
#1028
1&
0$
#1029
0&
1$
#1030
1&
0$
#1031
0&
1$
#1032
1&
0$
#1033
0&
1$
#1034
1&
0$
#1035
0&
1$
#1036
1&
0$
#1037
0&
1$
#1038
1&
0$
#1039
0&
1$
#1040
1&
0$
#1041
0&
1$
#1042
1&
0$
#1043
0&
1$
#1044
1&
0$
#1045
0&
1$
#1046
1&
0$
#1047
0&
1$
#1048
1&
0$
#1049
0&
1$
#1050
1&
0$
#1051
0&
1$
#1052
1&
0$
#1053
0&
1$
#1054
1&
0$
#1055
0&
1$
#1056
1&
0$
#1057
0&
1$
#1058
1&
0$
#1059
0&
1$
#1060
1&
0$
#1061
0&
1$
#1062
1&
0$
#1063
0&
1$
#1064
1&
0$
#1065
0&
1$
#1066
1&
0$
#1067
0&
1$
#1068
1&
0$
#1069
0&
1$
#1070
1&
0$
#1071
0&
1$
#1072
1&
0$
#1073
0&
1$
#1074
1&
0$
#1075
0&
1$
#1076
1&
0$
#1077
0&
1$
#1078
1&
0$
#1079
0&
1$
#1080
1&
0$
#1081
0&
1$
#1082
1&
0$
#1083
0&
1$
#1084
1&
0$
#1085
0&
1$
#1086
1&
0$
#1087
0&
1$
#1088
1&
0$
#1089
0&
1$
#1090
1&
0$
#1091
0&
1$
#1092
1&
0$
#1093
0&
1$
#1094
1&
0$
#1095
0&
1$
#1096
1&
0$
#1097
0&
1$
#1098
1&
0$
#1099
0&
1$
#1100
1&
0$
#1101
0&
1$
#1102
1&
0$
#1103
0&
1$
#1104
1&
0$
#1105
0&
1$
#1106
1&
0$
#1107
0&
1$
#1108
1&
0$
#1109
0&
1$
#1110
1&
0$
#1111
0&
1$
#1112
1&
0$
#1113
0&
1$
#1114
1&
0$
#1115
0&
1$
#1116
1&
0$
#1117
0&
1$
#1118
1&
0$
#1119
0&
1$
#1120
1&
0$
#1121
0&
1$
#1122
1&
0$
#1123
0&
1$
#1124
1&
0$
#1125
0&
1$
#1126
1&
0$
#1127
0&
1$
#1128
1&
0$
#1129
0&
1$
#1130
1&
0$
#1131
0&
1$
#1132
1&
0$
#1133
0&
1$
#1134
1&
0$
#1135
0&
1$
#1136
1&
0$
#1137
0&
1$
#1138
1&
0$
#1139
0&
1$
#1140
1&
0$
#1141
0&
1$
#1142
1&
0$
#1143
0&
1$
#1144
1&
0$
#1145
0&
1$
#1146
1&
0$
#1147
0&
1$
#1148
1&
0$
#1149
0&
1$
#1150
1&
0$
#1151
0&
1$
#1152
1&
0$
#1153
0&
1$
#1154
1&
0$
#1155
0&
1$
#1156
1&
0$
#1157
0&
1$
#1158
1&
0$
#1159
0&
1$
#1160
1&
0$
#1161
0&
1$
#1162
1&
0$
#1163
0&
1$
#1164
1&
0$
#1165
0&
1$
#1166
1&
0$
#1167
0&
1$
#1168
1&
0$
#1169
0&
1$
#1170
1&
0$
#1171
0&
1$
#1172
1&
0$
#1173
0&
1$
#1174
1&
0$
#1175
0&
1$
#1176
1&
0$
#1177
0&
1$
#1178
1&
0$
#1179
0&
1$
#1180
1&
0$
#1181
0&
1$
#1182
1&
0$
#1183
0&
1$
#1184
1&
0$
#1185
0&
1$
#1186
1&
0$
#1187
0&
1$
#1188
1&
0$
#1189
0&
1$
#1190
1&
0$
#1191
0&
1$
#1192
1&
0$
#1193
0&
1$
#1194
1&
0$
#1195
0&
1$
#1196
1&
0$
#1197
0&
1$
#1198
1&
0$
#1199
0&
1$
#1200
1&
0$
#1201
0&
1$
#1202
1&
0$
#1203
0&
1$
#1204
1&
0$
#1205
0&
1$
#1206
1&
0$
#1207
0&
1$
#1208
1&
0$
#1209
0&
1$
#1210
1&
0$
#1211
0&
1$
#1212
1&
0$
#1213
0&
1$
#1214
1&
0$
#1215
0&
1$
#1216
1&
0$
#1217
0&
1$
#1218
1&
0$
#1219
0&
1$
#1220
1&
0$
#1221
0&
1$
#1222
1&
0$
#1223
0&
1$
#1224
1&
0$
#1225
0&
1$
#1226
1&
0$
#1227
0&
1$
#1228
1&
0$
#1229
0&
1$
#1230
1&
0$
#1231
0&
1$
#1232
1&
0$
#1233
0&
1$
#1234
1&
0$
#1235
0&
1$
#1236
1&
0$
#1237
0&
1$
#1238
1&
0$
#1239
0&
1$
#1240
1&
0$
#1241
0&
1$
#1242
1&
0$
#1243
0&
1$
#1244
1&
0$
#1245
0&
1$
#1246
1&
0$
#1247
0&
1$
#1248
1&
0$
#1249
0&
1$
#1250
1&
0$
#1251
0&
1$
#1252
1&
0$
#1253
0&
1$
#1254
1&
0$
#1255
0&
1$
#1256
1&
0$
#1257
0&
1$
#1258
1&
0$
#1259
0&
1$
#1260
1&
0$
#1261
0&
1$
#1262
1&
0$
#1263
0&
1$
#1264
1&
0$
#1265
0&
1$
#1266
1&
0$
#1267
0&
1$
#1268
1&
0$
#1269
0&
1$
#1270
1&
0$
#1271
0&
1$
#1272
1&
0$
#1273
0&
1$
#1274
1&
0$
#1275
0&
1$
#1276
1&
0$
#1277
0&
1$
#1278
1&
0$
#1279
0&
1$
#1280
1&
0$
#1281
0&
1$
#1282
1&
0$
#1283
0&
1$
#1284
1&
0$
#1285
0&
1$
#1286
1&
0$
#1287
0&
1$
#1288
1&
0$
#1289
0&
1$
#1290
1&
0$
#1291
0&
1$
#1292
1&
0$
#1293
0&
1$
#1294
1&
0$
#1295
0&
1$
#1296
1&
0$
#1297
0&
1$
#1298
1&
0$
#1299
0&
1$
#1300
1&
0$
#1301
0&
1$
#1302
1&
0$
#1303
0&
1$
#1304
1&
0$
#1305
0&
1$
#1306
1&
0$
#1307
0&
1$
#1308
1&
0$
#1309
0&
1$
#1310
1&
0$
#1311
0&
1$
#1312
1&
0$
#1313
0&
1$
#1314
1&
0$
#1315
0&
1$
#1316
1&
0$
#1317
0&
1$
#1318
1&
0$
#1319
0&
1$
#1320
1&
0$
#1321
0&
1$
#1322
1&
0$
#1323
0&
1$
#1324
1&
0$
#1325
0&
1$
#1326
1&
0$
#1327
0&
1$
#1328
1&
0$
#1329
0&
1$
#1330
1&
0$
#1331
0&
1$
#1332
1&
0$
#1333
0&
1$
#1334
1&
0$
#1335
0&
1$
#1336
1&
0$
#1337
0&
1$
#1338
1&
0$
#1339
0&
1$
#1340
1&
0$
#1341
0&
1$
#1342
1&
0$
#1343
0&
1$
#1344
1&
0$
#1345
0&
1$
#1346
1&
0$
#1347
0&
1$
#1348
1&
0$
#1349
0&
1$
#1350
1&
0$
#1351
0&
1$
#1352
1&
0$
#1353
0&
1$
#1354
1&
0$
#1355
0&
1$
#1356
1&
0$
#1357
0&
1$
#1358
1&
0$
#1359
0&
1$
#1360
1&
0$
#1361
0&
1$
#1362
1&
0$
#1363
0&
1$
#1364
1&
0$
#1365
0&
1$
#1366
1&
0$
#1367
0&
1$
#1368
1&
0$
#1369
0&
1$
#1370
1&
0$
#1371
0&
1$
#1372
1&
0$
#1373
0&
1$
#1374
1&
0$
#1375
0&
1$
#1376
1&
0$
#1377
0&
1$
#1378
1&
0$
#1379
0&
1$
#1380
1&
0$
#1381
0&
1$
#1382
1&
0$
#1383
0&
1$
#1384
1&
0$
#1385
0&
1$
#1386
1&
0$
#1387
0&
1$
#1388
1&
0$
#1389
0&
1$
#1390
1&
0$
#1391
0&
1$
#1392
1&
0$
#1393
0&
1$
#1394
1&
0$
#1395
0&
1$
#1396
1&
0$
#1397
0&
1$
#1398
1&
0$
#1399
0&
1$
#1400
1&
0$
#1401
0&
1$
#1402
1&
0$
#1403
0&
1$
#1404
1&
0$
#1405
0&
1$
#1406
1&
0$
#1407
0&
1$
#1408
1&
0$
#1409
0&
1$
#1410
1&
0$
#1411
0&
1$
#1412
1&
0$
#1413
0&
1$
#1414
1&
0$
#1415
0&
1$
#1416
1&
0$
#1417
0&
1$
#1418
1&
0$
#1419
0&
1$
#1420
1&
0$
#1421
0&
1$
#1422
1&
0$
#1423
0&
1$
#1424
1&
0$
#1425
0&
1$
#1426
1&
0$
#1427
0&
1$
#1428
1&
0$
#1429
0&
1$
#1430
1&
0$
#1431
0&
1$
#1432
1&
0$
#1433
0&
1$
#1434
1&
0$
#1435
0&
1$
#1436
1&
0$
#1437
0&
1$
#1438
1&
0$
#1439
0&
1$
#1440
1&
0$
#1441
0&
1$
#1442
1&
0$
#1443
0&
1$
#1444
1&
0$
#1445
0&
1$
#1446
1&
0$
#1447
0&
1$
#1448
1&
0$
#1449
0&
1$
#1450
1&
0$
#1451
0&
1$
#1452
1&
0$
#1453
0&
1$
#1454
1&
0$
#1455
0&
1$
#1456
1&
0$
#1457
0&
1$
#1458
1&
0$
#1459
0&
1$
#1460
1&
0$
#1461
0&
1$
#1462
1&
0$
#1463
0&
1$
#1464
1&
0$
#1465
0&
1$
#1466
1&
0$
#1467
0&
1$
#1468
1&
0$
#1469
0&
1$
#1470
1&
0$
#1471
0&
1$
#1472
1&
0$
#1473
0&
1$
#1474
1&
0$
#1475
0&
1$
#1476
1&
0$
#1477
0&
1$
#1478
1&
0$
#1479
0&
1$
#1480
1&
0$
#1481
0&
1$
#1482
1&
0$
#1483
0&
1$
#1484
1&
0$
#1485
0&
1$
#1486
1&
0$
#1487
0&
1$
#1488
1&
0$
#1489
0&
1$
#1490
1&
0$
#1491
0&
1$
#1492
1&
0$
#1493
0&
1$
#1494
1&
0$
#1495
0&
1$
#1496
1&
0$
#1497
0&
1$
#1498
1&
0$
#1499
0&
1$
#1500
1&
0$
#1501
0&
1$
#1502
1&
0$
#1503
0&
1$
#1504
1&
0$
#1505
0&
1$
#1506
1&
0$
#1507
0&
1$
#1508
1&
0$
#1509
0&
1$
#1510
1&
0$
#1511
0&
1$
#1512
1&
0$
#1513
0&
1$
#1514
1&
0$
#1515
0&
1$
#1516
1&
0$
#1517
0&
1$
#1518
1&
0$
#1519
0&
1$
#1520
1&
0$
#1521
0&
1$
#1522
1&
0$
#1523
0&
1$
#1524
1&
0$
